MANIFEST.in
setup.cfg
setup.py
si_facenet/__init__.py
si_facenet.egg-info/PKG-INFO
si_facenet.egg-info/SOURCES.txt
si_facenet.egg-info/dependency_links.txt
si_facenet.egg-info/requires.txt
si_facenet.egg-info/top_level.txt
si_facenet/contributed/__init__.py
si_facenet/contributed/batch_represent.py
si_facenet/contributed/cluster.py
si_facenet/contributed/clustering.py
si_facenet/contributed/export_embeddings.py
si_facenet/contributed/face.py
si_facenet/contributed/predict.py
si_facenet/contributed/real_time_face_recognition.py
si_facenet/facenet/__init__.py
si_facenet/facenet/facenet.py
si_facenet/facenet/model_downloader.py
si_facenet/src/__init__.py
si_facenet/src/calculate_filtering_metrics.py
si_facenet/src/classifier.py
si_facenet/src/compare.py
si_facenet/src/decode_msceleb_dataset.py
si_facenet/src/download_and_extract.py
si_facenet/src/facenet.py
si_facenet/src/freeze_graph.py
si_facenet/src/lfw.py
si_facenet/src/train_softmax.py
si_facenet/src/train_tripletloss.py
si_facenet/src/validate_on_lfw.py
si_facenet/src/align/__init__.py
si_facenet/src/align/align_dataset_mtcnn.py
si_facenet/src/align/det1.npy
si_facenet/src/align/det2.npy
si_facenet/src/align/det3.npy
si_facenet/src/align/detect_face.py
si_facenet/src/generative/__init__.py
si_facenet/src/generative/calculate_attribute_vectors.py
si_facenet/src/generative/modify_attribute.py
si_facenet/src/generative/train_vae.py
si_facenet/src/generative/models/__init__.py
si_facenet/src/generative/models/dfc_vae.py
si_facenet/src/generative/models/dfc_vae_large.py
si_facenet/src/generative/models/dfc_vae_resnet.py
si_facenet/src/generative/models/vae_base.py
si_facenet/src/models/__init__.py
si_facenet/src/models/dummy.py
si_facenet/src/models/inception_resnet_v1.py
si_facenet/src/models/inception_resnet_v2.py
si_facenet/src/models/squeezenet.py
si_facenet/tmp/__init__.py
si_facenet/tmp/align_dataset.py
si_facenet/tmp/align_dlib.py
si_facenet/tmp/cacd2000_split_identities.py
si_facenet/tmp/dataset_read_speed.py
si_facenet/tmp/deepdream.py
si_facenet/tmp/download_vgg_face_dataset.py
si_facenet/tmp/funnel_dataset.py
si_facenet/tmp/mnist_center_loss.py
